channels_discord/__init__.py
channels_discord/cli.py
channels_discord/client.py
channels_discord/consumers.py
channels_discord-0.4.0.dist-info/LICENSE.txt
channels_discord-0.4.0.dist-info/METADATA
channels_discord-0.4.0.dist-info/WHEEL
channels_discord-0.4.0.dist-info/entry_points.txt
channels_discord-0.4.0.dist-info/top_level.txt
channels_discord-0.4.0.dist-info/RECORD
