Metadata-Version: 2.1
Name: channels-discord
Version: 0.4.0
Summary: Interface server connecting Django's channels and Discord
Home-page: https://github.com/AdvocatesInc/django-channels-discord
Author: Advocates Inc
Author-email: admin@adv.gg
License: MIT
Project-URL: Bug Tracker, https://github.com/AdvocatesInc/django-channels-discord/issues
Platform: UNKNOWN
Classifier: Environment :: Web Environment
Classifier: Framework :: Django
Classifier: Intended Audience :: Developers
Classifier: License :: OSI Approved :: MIT License
Classifier: Operating System :: OS Independent
Classifier: Programming Language :: Python
Classifier: Programming Language :: Python :: 3
Classifier: Programming Language :: Python :: 3.6
Classifier: Programming Language :: Python :: 3.7
Classifier: Programming Language :: Python :: 3.8
Classifier: Programming Language :: Python :: 3.9
Requires-Python: >=3.6
License-File: LICENSE.txt
Requires-Dist: py-cord (>=1.7.3)
Requires-Dist: channels (>=3.0.0)
